easilyai/__init__.py
easilyai/app.py
easilyai/custom_ai.py
easilyai/exceptions.py
easilyai/pipeline.py
easilyai/utils.py
easilyai/services/__init__.py
easilyai/services/anthropic_service.py
easilyai/services/gemini_service.py
easilyai/services/grok_service.py
easilyai/services/ollama_service.py
easilyai/services/openai_service.py
EasilyAI-0.2.1.dist-info/LICENSE
EasilyAI-0.2.1.dist-info/METADATA
EasilyAI-0.2.1.dist-info/WHEEL
EasilyAI-0.2.1.dist-info/top_level.txt
EasilyAI-0.2.1.dist-info/RECORD
